{
  "room": {
    "width": 800,
    "height": 600
  },
  "furniture": [
    {
      "name": "Bed",
      "x": 310,
      "y": 370,
      "width": 180,
      "height": 180,
      "zHeight": "55",
      "rotation": 180
    },
    {
      "name": "Study Table",
      "x": 290,
      "y": 30,
      "width": 120,
      "height": 120,
      "zHeight": "75",
      "rotation": 0
    },
    {
      "name": "Study Chair",
      "x": 320,
      "y": 40,
      "width": 50,
      "height": 50,
      "zHeight": "90",
      "rotation": 0
    },
    {
      "name": "Sofa",
      "x": 580,
      "y": 30,
      "width": 200,
      "height": 200,
      "zHeight": "85",
      "rotation": 0
    }
  ],
  "openings": [
    {
      "type": "door",
      "wall": "left",
      "position": 249,
      "size": 90,
      "openingHeight": "210"
    },
    {
      "type": "window",
      "wall": "top",
      "position": 404,
      "size": 120,
      "openingHeight": "100",
      "heightFromGround": "90"
    }
  ]
}